nereid/__init__.py
nereid/application.py
nereid/caching.py
nereid/config.py
nereid/csrf.py
nereid/ctx.py
nereid/exceptions.py
nereid/globals.py
nereid/helpers.py
nereid/logging.py
nereid/routing.py
nereid/sessions.py
nereid/signals.py
nereid/templating.py
nereid/testing.py
nereid/wrappers.py
nereid/contrib/__init__.py
nereid/contrib/locale.py
nereid/contrib/pagination.py
nereid/contrib/sitemap.py
nereid/tests/__init__.py
nereid/tests/test_dispatch.py
nereid/tests/test_helpers.py
nereid/tests/test_module.py
nereid/tests/test_pagination.py
nereid/tests/test_signals.py
nereid/tests/test_templates.py
trytond/modules/nereid_test/__init__.py
trytond/modules/nereid_test/model.py
trytond/modules/nereid_test/setup.py
trytond/modules/nereid_test/tryton.cfg
trytond/modules/nereid_test/templates/registration.jinja
trytond/modules/nereid_test/templates/tests/from-module.html
trytond/modules/nereid_test/templates/tests/test-changing-context.html
trytond/modules/nereid_test/templates/tests/translation-test.html
m9s_nereid-7.0.12.dist-info/LICENSE
m9s_nereid-7.0.12.dist-info/LICENSE.BSD
m9s_nereid-7.0.12.dist-info/LICENSE.GPL3
m9s_nereid-7.0.12.dist-info/METADATA
m9s_nereid-7.0.12.dist-info/WHEEL
m9s_nereid-7.0.12.dist-info/top_level.txt
m9s_nereid-7.0.12.dist-info/RECORD
