Metadata-Version: 2.1
Name: m9s-nereid
Version: 7.0.12
Summary: Tryton Nereid Module
Home-page: https://www.m9s.biz/
Download-URL: https://gitlab.com/m9s/nereid.git
Author: MBSolutions
Author-email: info@m9s.biz
License: GPL-3
Project-URL: Bug Tracker, https://support.m9s.biz/
Project-URL: Source Code, https://gitlab.com/m9s/nereid.git
Classifier: Development Status :: 5 - Production/Stable
Classifier: Environment :: Plugins
Classifier: Framework :: Tryton
Classifier: Intended Audience :: Developers
Classifier: Intended Audience :: Financial and Insurance Industry
Classifier: Intended Audience :: Legal Industry
Classifier: License :: OSI Approved :: GNU General Public License v3 or later (GPLv3+)
Classifier: Natural Language :: Bulgarian
Classifier: Natural Language :: Catalan
Classifier: Natural Language :: Chinese (Simplified)
Classifier: Natural Language :: Czech
Classifier: Natural Language :: Dutch
Classifier: Natural Language :: English
Classifier: Natural Language :: Finnish
Classifier: Natural Language :: French
Classifier: Natural Language :: German
Classifier: Natural Language :: Hungarian
Classifier: Natural Language :: Indonesian
Classifier: Natural Language :: Italian
Classifier: Natural Language :: Persian
Classifier: Natural Language :: Polish
Classifier: Natural Language :: Portuguese (Brazilian)
Classifier: Natural Language :: Romanian
Classifier: Natural Language :: Russian
Classifier: Natural Language :: Slovenian
Classifier: Natural Language :: Spanish
Classifier: Natural Language :: Turkish
Classifier: Natural Language :: Ukrainian
Classifier: Operating System :: OS Independent
Classifier: Programming Language :: Python :: 3
Classifier: Programming Language :: Python :: 3.8
Classifier: Programming Language :: Python :: 3.9
Classifier: Programming Language :: Python :: 3.10
Classifier: Programming Language :: Python :: 3.11
Classifier: Programming Language :: Python :: 3.12
Classifier: Programming Language :: Python :: Implementation :: CPython
Classifier: Topic :: Office/Business
Requires-Python: >=3.8
License-File: LICENSE
License-File: LICENSE.BSD
License-File: LICENSE.GPL3
Requires-Dist: Flask-Babel
Requires-Dist: Flask-Login
Requires-Dist: blinker
Requires-Dist: cachelib
Requires-Dist: email-validator
Requires-Dist: flask
Requires-Dist: flask-wtf
Requires-Dist: m9s-nereid-base <7.1,>=7.0
Requires-Dist: pytz
Requires-Dist: secure-cookie
Requires-Dist: speaklater
Provides-Extra: test
Requires-Dist: m9s-nereid-base <7.1,>=7.0 ; extra == 'test'
Requires-Dist: m9s-nereid-test <7.1,>=7.0 ; extra == 'test'
Requires-Dist: pycountry >=16.11.08 ; extra == 'test'
